dbally/__init__.py
dbally/__version__.py
dbally/_main.py
dbally/_types.py
dbally/exceptions.py
dbally/py.typed
dbally/assistants/__init__.py
dbally/assistants/base.py
dbally/assistants/openai.py
dbally/audit/__init__.py
dbally/audit/event_tracker.py
dbally/audit/events.py
dbally/audit/spans.py
dbally/audit/event_handlers/__init__.py
dbally/audit/event_handlers/base.py
dbally/audit/event_handlers/buffer_event_handler.py
dbally/audit/event_handlers/cli_event_handler.py
dbally/audit/event_handlers/langsmith_event_handler.py
dbally/audit/event_handlers/otel_event_handler.py
dbally/collection/__init__.py
dbally/collection/collection.py
dbally/collection/exceptions.py
dbally/collection/results.py
dbally/embeddings/__init__.py
dbally/embeddings/base.py
dbally/embeddings/exceptions.py
dbally/embeddings/litellm.py
dbally/gradio/__init__.py
dbally/gradio/interface.py
dbally/iql/__init__.py
dbally/iql/_exceptions.py
dbally/iql/_processor.py
dbally/iql/_query.py
dbally/iql/_type_validators.py
dbally/iql/syntax.py
dbally/iql_generator/__init__.py
dbally/iql_generator/iql_generator.py
dbally/iql_generator/prompt.py
dbally/llms/__init__.py
dbally/llms/base.py
dbally/llms/litellm.py
dbally/llms/local.py
dbally/llms/clients/__init__.py
dbally/llms/clients/base.py
dbally/llms/clients/exceptions.py
dbally/llms/clients/litellm.py
dbally/llms/clients/local.py
dbally/nl_responder/__init__.py
dbally/nl_responder/nl_responder.py
dbally/nl_responder/prompts.py
dbally/prompt/__init__.py
dbally/prompt/elements.py
dbally/prompt/template.py
dbally/similarity/__init__.py
dbally/similarity/chroma_store.py
dbally/similarity/elastic_vector_search.py
dbally/similarity/elasticsearch_store.py
dbally/similarity/faiss_store.py
dbally/similarity/fetcher.py
dbally/similarity/index.py
dbally/similarity/sqlalchemy_base.py
dbally/similarity/store.py
dbally/view_selection/__init__.py
dbally/view_selection/base.py
dbally/view_selection/llm_view_selector.py
dbally/view_selection/prompt.py
dbally-0.8.0.dist-info/licenses/LICENSE
dbally-0.8.0.dist-info/METADATA
dbally-0.8.0.dist-info/WHEEL
dbally-0.8.0.dist-info/entry_points.txt
dbally-0.8.0.dist-info/top_level.txt
dbally-0.8.0.dist-info/RECORD
