Metadata-Version: 2.4
Name: dbally
Version: 0.8.0
Summary: "Efficient, consistent and secure library for querying structured data with natural language"
Author: deepsense.ai
Author-email: contact@deepsense.ai
License: MIT
Project-URL: Documentation, https://db-ally.deepsense.ai/
Project-URL: Source, https://github.com/deepsense-ai/db-ally
Classifier: Development Status :: 2 - Pre-Alpha
Classifier: Environment :: Console
Classifier: Intended Audience :: Developers
Classifier: License :: OSI Approved :: MIT License
Classifier: Natural Language :: English
Classifier: Programming Language :: Python :: 3.8
Classifier: Programming Language :: Python :: 3.9
Classifier: Programming Language :: Python :: 3.10
Classifier: Programming Language :: Python :: 3.11
Classifier: Programming Language :: Python :: 3.12
Requires-Python: >=3.8
License-File: LICENSE
Requires-Dist: pandas~=2.0.3
Requires-Dist: python-dotenv>=0.5.1
Requires-Dist: SQLAlchemy==2.0.25
Requires-Dist: tabulate>=0.9.0
Requires-Dist: click~=8.1.7
Requires-Dist: numpy>=1.24.0
Requires-Dist: opentelemetry-api>=1.0.0
Provides-Extra: litellm
Requires-Dist: litellm>=1.37.9; extra == "litellm"
Provides-Extra: faiss
Requires-Dist: faiss-cpu>=1.8.0; extra == "faiss"
Provides-Extra: chromadb
Requires-Dist: chromadb~=0.4.24; extra == "chromadb"
Requires-Dist: posthog~=3.8.3; extra == "chromadb"
Requires-Dist: tenacity~=8.3.0; extra == "chromadb"
Provides-Extra: langsmith
Requires-Dist: langsmith~=0.1.57; extra == "langsmith"
Provides-Extra: elasticsearch
Requires-Dist: elasticsearch~=8.13.1; extra == "elasticsearch"
Provides-Extra: gradio
Requires-Dist: gradio~=4.31.5; extra == "gradio"
Requires-Dist: gradio_client~=0.16.4; extra == "gradio"
Provides-Extra: local
Requires-Dist: accelerate~=0.31.0; extra == "local"
Requires-Dist: torch~=2.2.1; extra == "local"
Requires-Dist: transformers~=4.41.2; extra == "local"
Provides-Extra: dev
Requires-Dist: datasets~=2.20.0; extra == "dev"
Requires-Dist: dspy-ai~=2.4.13; extra == "dev"
Requires-Dist: hydra-core~=1.3.2; extra == "dev"
Requires-Dist: neptune~=1.6.3; extra == "dev"
Requires-Dist: pydantic~=2.6.0; extra == "dev"
Requires-Dist: pydantic_settings~=2.1.0; extra == "dev"
Requires-Dist: psycopg2-binary~=2.9.9; extra == "dev"
Dynamic: license-file
